[{"id":1,"name":"Rosa","lastname":"Gonzales","email":"rosa.gonzales@gmail.com","password":"12345678","rol":"ROL_USER","city":"","phone":"","address":"","zipCode":"","avatar":"image-avatar-default"},{"id":2,"name":"jeane","lastname":"garcia barrera","email":"jeane@gmail.com","password":"$2a$12$t6B7umCk.MJFX7DXNszcF.npv1Vgl4KEAXkgvbALE1LeFA0Gz0js.","rol":"ROL_USER","city":"","phone":"","address":"","zipCode":"","avatar":"image-avatar-default"},{"id":3,"name":"jeanette","lastname":"garcia barrera","email":"jeanette.garcia@gmail.com","password":"$2a$12$d/AciCJ/WW82l0WJ6G1q4OhsCiTBJDjXDNAdmLshIR9YywYmfOaRC","rol":"ROL_USER","city":"","phone":"","address":"","zipCode":"","avatar":"image-avatar-default"},{"id":4,"name":"jeanette","lastname":"garcia barrera","email":"jeanette.gb@gmail.com","password":"$2a$12$a8Ov/TX1tgqZTVV6.ahoJusQlwmr5PEA4qGS5juA6QKe91EcNMOIG","rol":"ROL_USER","city":"lalal","phone":"11112","address":"lslsls","avatar":"1641546777758_img_.png"}]